consolidatedrms/__init__.py
consolidatedrms/consolidatedrms.py
consolidatedrms-0.4.dist-info/LICENSE
consolidatedrms-0.4.dist-info/METADATA
consolidatedrms-0.4.dist-info/WHEEL
consolidatedrms-0.4.dist-info/top_level.txt
consolidatedrms-0.4.dist-info/RECORD
