Metadata-Version: 2.1
Name: consolidatedrms
Version: 0.4
Summary: Python library for Zerodha RMS consolidated scrips
Home-page: https://github.com/zerodhatech/rms-consolidated-scrips-status
Author: Rakesh R
Author-email: rrrakesh265@gmail.com
License: UNKNOWN
Platform: UNKNOWN
Classifier: Programming Language :: Python :: 3
Classifier: License :: OSI Approved :: MIT License
Classifier: Topic :: Software Development :: Libraries
Requires-Dist: pandas
